qclipx/__init__.py
qclipx/qclipx.py
qclipx-1.0.2.dist-info/LICENSE
qclipx-1.0.2.dist-info/METADATA
qclipx-1.0.2.dist-info/WHEEL
qclipx-1.0.2.dist-info/entry_points.txt
qclipx-1.0.2.dist-info/top_level.txt
qclipx-1.0.2.dist-info/RECORD
