Metadata-Version: 2.1
Name: qclipx
Version: 1.0.2
Summary: Cross platform clipboard tool
Home-page: https://github.com/timxx/qclipx
Author: Weitian Leung
Author-email: weitianleung@gmail.com
License: MIT
Keywords: clipboard tool viewer
Classifier: License :: OSI Approved :: MIT License
Classifier: Operating System :: POSIX
Classifier: Operating System :: POSIX :: BSD
Classifier: Operating System :: POSIX :: Linux
Classifier: Operating System :: Microsoft :: Windows
Classifier: Programming Language :: Python :: 3
Requires-Python: >=3.0
License-File: LICENSE
Requires-Dist: PySide6-Essentials >=6.3.0
Requires-Dist: pyhexedit
